{
  "schema_version": "dahash.hash_type/v1",
  "id": "sha224-pass-salt",
  "name": "sha224($pass.$salt)",
  "status": "active",
  "tags": [
    "extended"
  ],
  "priority": 20,
  "matchers": [
    {
      "id": "sha224-pass-salt.haiti.049",
      "kind": "regex",
      "scope": "token",
      "pattern": "^[a-f0-9]{56}(?::.+)?$",
      "confidence": "weak",
      "weight": 25,
      "sources": [
        {
          "id": "haiti",
          "ref": "\\A[a-f0-9]{56}(?::.+)?\\Z"
        }
      ]
    }
  ],
  "tools": {
    "hashcat": [
      {
        "mode": 1310,
        "name": "sha224($pass.$salt)",
        "status": "active",
        "sources": [
          {
            "id": "haiti",
            "ref": "1310"
          },
          {
            "id": "hashcat-examples",
            "ref": "1310"
          }
        ]
      }
    ],
    "john": [
      {
        "format": "dynamic_52",
        "name": "sha224($pass.$salt)",
        "status": "active",
        "sources": [
          {
            "id": "haiti",
            "ref": "dynamic_52"
          }
        ]
      }
    ]
  },
  "examples": [
    {
      "kind": "inline",
      "value": "0cf361904f4b0234cf4ade8496d8c11c04e5982db967603e82f22b2f:89452466460220844541730694146873525188525677",
      "sources": [
        {
          "id": "haiti",
          "ref": "sha224($pass.$salt)"
        },
        {
          "id": "hashcat-examples",
          "ref": "1310"
        }
      ]
    }
  ],
  "sources": [
    {
      "id": "haiti",
      "ref": "sha224($pass.$salt)"
    }
  ]
}
