{
  "schema_version": "dahash.hash_type/v1",
  "id": "sha256-sha256-pass-sha256-pass",
  "name": "sha256(sha256($pass).sha256($pass))",
  "status": "active",
  "tags": [
    "extended"
  ],
  "priority": 20,
  "matchers": [
    {
      "id": "sha256-sha256-pass-sha256-pass.haiti.058",
      "kind": "regex",
      "scope": "token",
      "pattern": "^[a-f0-9]{64}(:.+)?$",
      "confidence": "weak",
      "weight": 25,
      "sources": [
        {
          "id": "haiti",
          "ref": "\\A[a-f0-9]{64}(:.+)?\\Z"
        }
      ]
    }
  ],
  "tools": {
    "john": [
      {
        "format": "dynamic_68",
        "name": "sha256(sha256($pass).sha256($pass))",
        "status": "active",
        "sources": [
          {
            "id": "haiti",
            "ref": "dynamic_68"
          }
        ]
      }
    ]
  },
  "sources": [
    {
      "id": "haiti",
      "ref": "sha256(sha256($pass).sha256($pass))"
    }
  ]
}
