{
  "schema_version": "dahash.hash_type/v1",
  "id": "shangmi-3-sm3",
  "name": "ShangMi 3 (SM3)",
  "status": "active",
  "tags": [
    "hashcat"
  ],
  "priority": 50,
  "sources": [
    {
      "id": "hashcat-examples",
      "ref": "31100"
    }
  ],
  "tools": {
    "hashcat": [
      {
        "mode": 31100,
        "name": "ShangMi 3 (SM3)",
        "status": "active",
        "sources": [
          {
            "id": "hashcat-examples",
            "ref": "31100"
          }
        ]
      }
    ]
  },
  "examples": [
    {
      "kind": "inline",
      "value": "51227e48ea74827b77fc142c3ec21d25cc42c794e6ac422825cd47ad4ac7913d",
      "verified": true,
      "sources": [
        {
          "id": "hashcat-examples",
          "ref": "31100"
        }
      ],
      "plaintext": "hashcat"
    }
  ],
  "matchers": [
    {
      "id": "shangmi-3-sm3.hashcat.31100",
      "kind": "regex",
      "scope": "token",
      "pattern": "^[A-Fa-f0-9]{64}$",
      "confidence": "strong",
      "weight": 40,
      "sources": [
        {
          "id": "hashcat-examples",
          "ref": "31100"
        }
      ]
    }
  ]
}
