{
  "schema_version": "dahash.hash_type/v2",
  "id": "veracrypt-sha256-xts-1536-bit-legacy",
  "name": "VeraCrypt SHA256 + XTS 1536 bit (legacy)",
  "aliases": [
    "VeraCrypt SHA256 + XTS 1536 bit (legacy)"
  ],
  "status": "active",
  "priority": 50,
  "extraction": {
    "supported": false,
    "inputs": [],
    "converters": []
  },
  "tools": {
    "hashcat": [
      {
        "mode": 13753,
        "name": "VeraCrypt SHA256 + XTS 1536 bit (legacy)",
        "status": "active"
      }
    ]
  },
  "identification": {
    "max_confidence": 45
  },
  "match": {
    "base": 10,
    "total": 50,
    "requires": [
      {
        "feature": "regex",
        "args": {
          "regex": "\\A[a-f0-9]{1024}\\Z",
          "flags": [
            "i"
          ]
        },
        "id": "required_pattern"
      }
    ],
    "evidence": [
      {
        "feature": "regex",
        "args": {
          "regex": "\\A[a-f0-9]{1024}\\Z",
          "flags": [
            "i"
          ]
        },
        "id": "pattern_match",
        "weight": 40
      }
    ]
  }
}
